MANIFEST.in
README.md
ez_setup.py
setup.py
metaphor/__init__.py
metaphor/cythonlist.txt
metaphor/version_nntoolbox.py
metaphor/nntoolbox/__init__.py
metaphor/nntoolbox/cleaner.py
metaphor/nntoolbox/cmd_line_dialogs.c
metaphor/nntoolbox/configparsertoolbox.c
metaphor/nntoolbox/constants.py
metaphor/nntoolbox/dataset.c
metaphor/nntoolbox/dockercleaner.py
metaphor/nntoolbox/essai.py
metaphor/nntoolbox/essais.py
metaphor/nntoolbox/excelutils.c
metaphor/nntoolbox/filetoolbox.c
metaphor/nntoolbox/hookable.c
metaphor/nntoolbox/lineartoolbox.c
metaphor/nntoolbox/modelutils.c
metaphor/nntoolbox/progress.c
metaphor/nntoolbox/sqlite_numpy.c
metaphor/nntoolbox/template.py
metaphor/nntoolbox/test.py
metaphor/nntoolbox/timetb.c
metaphor/nntoolbox/updateFileContent.py
metaphor/nntoolbox/utils.c
metaphor/nntoolbox/datareader/__init__.py
metaphor/nntoolbox/datareader/_excel.c
metaphor/nntoolbox/datareader/check_sigs.c
metaphor/nntoolbox/datareader/datasource.c
metaphor/nntoolbox/datareader/excelsource.c
metaphor/nntoolbox/datareader/fileInspect.c
metaphor/nntoolbox/datareader/modeldataframe.py
metaphor/nntoolbox/toktoolbox/__init__.py
metaphor/nntoolbox/toktoolbox/tokens.py
metaphor_nntoolbox.egg-info/PKG-INFO
metaphor_nntoolbox.egg-info/SOURCES.txt
metaphor_nntoolbox.egg-info/dependency_links.txt
metaphor_nntoolbox.egg-info/not-zip-safe
metaphor_nntoolbox.egg-info/requires.txt
metaphor_nntoolbox.egg-info/top_level.txt